[
 {
  "table":"TADIR",
  "data":
  [
   {
    "PGMID":"R3TR",
    "OBJECT":"SUSH",
    "OBJ_NAME":"1ED250D2849919677BAED8F0F918B9HT",
    "KORRNUM":"",
    "SRCSYSTEM":"...",
    "AUTHOR":"SAP_CUSTOMER",
    "SRCDEP":"",
    "DEVCLASS":"YPAYMENT",
    "GENFLAG":"",
    "EDTFLAG":"",
    "CPROJECT":" L",
    "MASTERLANG":"T",
    "VERSID":"",
    "PAKNOCHECK":"",
    "OBJSTABLTY":"",
    "COMPONENT":"",
    "CRELEASE":"",
    "DELFLAG":"",
    "TRANSLTTXT":"",
    "CREATED_ON":"2024-09-11",
    "CHECK_DATE":"2024-09-11",
    "CHECK_CFG":""
   }
  ]
 },
 {
  "table":"USOBHASH",
  "data":
  [
   {
    "NAME":"1ED250D2849919677BAED8F0F918B9",
    "TYPE":"HT",
    "PGMID":"R3TR",
    "OBJECT":"IWSV",
    "OBJ_NAME":"YSB_APPROVEMENT_CUS                0001",
    "SERVICE_TYPE":"",
    "SERVICE":""
   }
  ]
 },
 {
  "table":"USOBX",
  "data":
  [
   {
    "NAME":"1ED250D2849919677BAED8F0F918B9",
    "TYPE":"HT",
    "OBJECT":"S_SERVICE",
    "MODIFIER":"SAP_CUSTOMER",
    "MODDATE":"2024-09-11",
    "MODTIME":"14:13:15",
    "OKFLAG":"X"
   }
  ]
 },
 {
  "table":"USOB_SM",
  "data":
  [
   {
    "NAME":"1ED250D2849919677BAED8F0F918B9",
    "TYPE":"HT",
    "MODIFIER":"SAP_CUSTOMER",
    "MODDATE":"2024-09-11",
    "MODTIME":"14:13:15",
    "OKFLAG":"",
    "ATTRIBUTES":"",
    "ABAP_LANGUAGE_VERSION":"5"
   }
  ]
 }
]